deeprecon/__init__.py
deeprecon/availability.py
deeprecon/cli.py
deeprecon/config.py
deeprecon/dns.py
deeprecon/geoip.py
deeprecon/network.py
deeprecon/resolve.py
deeprecon/security.py
deeprecon/ssl.py
deeprecon/tech_detect.py
deeprecon/whois.py
deeprecon/locales/en.json
deeprecon/locales/fa.json
deeprecon/utils/__init__.py
deeprecon/utils/formatter.py
deeprecon/utils/network_utils.py
deeprecon/utils/validator.py
deeprecon-1.1.0.dist-info/licenses/LICENSE
deeprecon-1.1.0.dist-info/METADATA
deeprecon-1.1.0.dist-info/WHEEL
deeprecon-1.1.0.dist-info/entry_points.txt
deeprecon-1.1.0.dist-info/top_level.txt
deeprecon-1.1.0.dist-info/RECORD
