Metadata-Version: 2.4
Name: deeprecon
Version: 1.1.0
Summary: A powerful, modular Python library for comprehensive domain and IP analysis
Home-page: https://github.com/DeepPythonist/DeepRecon
Author: Mohammad Rasol Esfandiari
Author-email: Mohammad Rasol Esfandiari <mrasolesfandiari@gmail.com>
License: MIT License
Project-URL: Homepage, https://github.com/DeepPythonist/DeepRecon
Project-URL: Repository, https://github.com/DeepPythonist/DeepRecon
Project-URL: Documentation, https://github.com/DeepPythonist/DeepRecon#readme
Project-URL: Changelog, https://github.com/DeepPythonist/DeepRecon/blob/main/CHANGELOG.md
Project-URL: Bug Reports, https://github.com/DeepPythonist/DeepRecon/issues
Keywords: domain,ip,dns,whois,ssl,security,networking,reconnaissance,analysis,geolocation
Classifier: Development Status :: 5 - Production/Stable
Classifier: Intended Audience :: Developers
Classifier: Intended Audience :: System Administrators
Classifier: License :: OSI Approved :: MIT License
Classifier: Operating System :: OS Independent
Classifier: Programming Language :: Python :: 3
Classifier: Programming Language :: Python :: 3.8
Classifier: Programming Language :: Python :: 3.9
Classifier: Programming Language :: Python :: 3.10
Classifier: Programming Language :: Python :: 3.11
Classifier: Programming Language :: Python :: 3.12
Classifier: Topic :: Internet :: WWW/HTTP
Classifier: Topic :: Security
Classifier: Topic :: System :: Networking
Requires-Python: >=3.8
License-File: LICENSE
Requires-Dist: requests>=2.31.0
Requires-Dist: dnspython>=2.4.2
Requires-Dist: python-whois>=0.8.0
Requires-Dist: ipwhois>=1.2.0
Requires-Dist: pyOpenSSL>=23.3.0
Requires-Dist: beautifulsoup4>=4.12.2
Requires-Dist: lxml>=4.9.3
Requires-Dist: psutil>=5.9.0
Requires-Dist: netifaces>=0.11.0
Requires-Dist: speedtest-cli>=2.1.3
Provides-Extra: dev
Requires-Dist: pytest>=7.0.0; extra == "dev"
Requires-Dist: pytest-cov>=4.0.0; extra == "dev"
Requires-Dist: flake8>=5.0.0; extra == "dev"
Requires-Dist: black>=22.0.0; extra == "dev"
Requires-Dist: isort>=5.0.0; extra == "dev"
Dynamic: author
Dynamic: home-page
Dynamic: license-file
Dynamic: requires-python
